{
  "required": true,
  "minVersion": "0.8",
  "package": "net.wubz.wubzmod.mixin",
  "compatibilityLevel": "JAVA_17",
  "mixins": [
  ],
  "client": [
    "TitleScreenMixin",
    "GameMenuScreenMixin",
    "GameInfoMixin",
    "MinecraftClientMixin",
    "BlockMixin",
    "PlayerMoveC2SPacketMixin",
    "PlayerC2SPacketPositionAndOnGroundMixin",
    "VehicleMoveC2SPacketMixin",
    "GameStateChangeS2CPacketMixin",
    "WorldBorderInitializeS2CPacketMixin"
  ],
  "injectors": {
    "defaultRequire": 1
  }
}
